MatRocket/CHANGELOG.md
MatRocket/CONTRIBUTING.md
MatRocket/ETHICS.md
MatRocket/README.md
MatRocket/__init__.py
MatRocket/BlenderAssets/__init__.py
MatRocket/Debug/__init__.py
MatRocket/Debug/Unit_Tests/__init__.py
MatRocket/Debug/Unit_Tests/area_moments_tester.m
MatRocket/Debug/Unit_Tests/blender2matlab_tester.m
MatRocket/Debug/Unit_Tests/images2vid.m
MatRocket/Debug/Unit_Tests/mesh2mesh_path.m
MatRocket/Documentation/__init__.py
MatRocket/Documentation/aerodynamics_model.md
MatRocket/Documentation/lib/__init__.py
MatRocket/Documentation/lib/area_element.m
MatRocket/Documentation/lib/area_moment_terms.m
MatRocket/Documentation/lib/area_projected.m
MatRocket/Documentation/lib/basis.m
MatRocket/Documentation/lib/center_of_pressure_animation.m
MatRocket/Documentation/lib/force_distribution.m
MatRocket/Documentation/lib/integrand.m
MatRocket/Documentation/lib/integrand_approximation.m
MatRocket/Documentation/lib/perm.m
MatRocket/Documentation/lib/trim_historian.m
MatRocket/Documentation/lib/velocity_distribution.m
MatRocket/Simulation/__init__.py
MatRocket/Simulation/rocket.m
MatRocket/Simulation/run_simulation.m
MatRocket/Simulation/Models/__init__.py
MatRocket/Simulation/Models/base_UI_loading_bar.m
MatRocket/Simulation/Models/base_aerodynamics_model.m
MatRocket/Simulation/Models/base_atmosphere_from_dataset_model.m
MatRocket/Simulation/Models/base_atmosphere_model.m
MatRocket/Simulation/Models/base_equations_of_motion_model.m
MatRocket/Simulation/Models/base_gravity_model.m
MatRocket/Simulation/Models/base_propulsion_model.m
MatRocket/Simulation/Models/lib/__init__.py
MatRocket/Simulation/Models/lib/body.m
MatRocket/Simulation/Models/lib/cellsum.m
MatRocket/Simulation/Models/lib/derivative2vector.m
MatRocket/Simulation/Models/lib/force_vector.m
MatRocket/Simulation/Models/lib/limit.m
MatRocket/Simulation/Models/lib/mesh2aerodynamics.m
MatRocket/Simulation/Models/lib/moment_vector.m
MatRocket/Simulation/Models/lib/normalize.m
matrocket-0.10.18.dist-info/METADATA
matrocket-0.10.18.dist-info/WHEEL
matrocket-0.10.18.dist-info/top_level.txt
matrocket-0.10.18.dist-info/RECORD
