Metadata-Version: 2.4
Name: MatRocket
Version: 0.10.18
Summary: MatRocket is a library for simulating rockets in MATLAB.
Home-page: https://github.com/spiggen/MatRocket
Author: Vilgot Lötberg
Author-email: vilgotl@kth.se
Requires-Python: >=3.6
Requires-Dist: MatlabBlenderIO
Dynamic: author
Dynamic: author-email
Dynamic: description
Dynamic: description-content-type
Dynamic: home-page
Dynamic: requires-dist
Dynamic: requires-python
Dynamic: summary
